{
  "updateTime": "2026-05-24 04:30",
  "forex": {
    "icon": "💱",
    "title": "外汇提示",
    "text": "美元指数104.5，日元160关口",
    "detail": "日元兑美元汇率跌破160心理关口，创34年新低。日本财务省官员发出警告，表示将采取适当措施应对汇率过度波动。美日利差持续扩大是贬值主因，日本央行加息预期推迟至7月。短期日元仍承压，投资者需关注日本央行干预风险。美元指数维持在104.5附近，非美货币普遍承压。"
  },
  "stock": {
    "icon": "📈",
    "title": "股市动向",
    "text": "A股放量上涨，北向资金连续4日净流入",
    "detail": "A股三大指数全线收涨，沪指重返3400点。成交额突破万亿，北向资金净流入超80亿，连续4个交易日净流入累计超300亿。券商、新能源、半导体领涨，外资重点加仓白酒和新能源板块。市场情绪回暖，技术面看3450点是短期压力位，突破则打开上涨空间。"
  }
}
