{
  "updateTime": "2026-05-27 15:32",
  "forex": {
    "icon": "💱",
    "title": "外汇提示",
    "text": "欧洲央行6月加息概率上升，欧元走强；新西兰央行维持利率不变但释放加息信号，暗示全球紧缩周期未结束。",
    "detail": "欧洲央行管委Stournaras明确表示6月加息是最可能的情形，中东冲突持续推高能源价格导致通胀压力持续。欧元兑人民币升至7.90附近，美元兑人民币报6.78。新西兰央行以微弱票数决议维持利率不变，同时释放加息信号，观望中东局势对通胀影响。澳大利亚通胀有所回落但仍保留加息可能性。美联储卡什卡利表示美国通胀风险高于劳动力市场风险，暗示政策转向仍需时日。日本政府将于6月3日向国会提交补充预算案。人民币汇率整体维持区间震荡，央行维持维稳基调。中东局势方面，伊朗革命卫队海军称将对\"侵略者\"实施严厉报复，布伦特原油短线拉升。建议关注今日欧洲通胀数据和下周美国PCE数据对汇率的影响。"
  },
  "stock": {
    "icon": "📈",
    "title": "股市动向",
    "text": "A股沪指跌1.25%失守4100点，白酒逆势大涨；创业板微涨0.07%；成交额3.24万亿。",
    "detail": "A股三大指数分化明显：上证指数收报4093.73点跌1.25%失守4100点，深证成指跌0.88%报15736.47点，创业板指微涨0.07%报4045.77点。沪深两市成交额3.24万亿，连续第3日突破3万亿。板块方面：白酒股逆势大涨（水井坊涨停、舍得酒业、金徽酒触及涨停），短剧概念活跃（百纳千成、欢瑞世纪、掌阅科技涨停），煤炭电力板块拉升（华电能源涨停）。科创50大跌2.80%领跌各指数。港股方面，恒生指数收跌1.13%报25310点，恒生科技跌1.2%。智谱总市值超6500亿港元，盘中再创历史新高。美股方面，纳斯达克指数收报26656点涨1.19%再创历史新高，标普500涨0.61%报7519点。欧洲三大股指开盘走高，斯托克50涨0.6%。高盛将标普500年底目标上调至8000点。北向资金今日净流出，前期涨幅较大的科技板块获利回吐，资金转向防御型资产（白酒、电力板块）。半导体板块集体回调，但中韩半导体ETF仍收涨超5%。"
  }
}
