{
  "updateTime": "2026-05-25 21:25",
  "generatedAt": "2026-05-25 21:25",
  "mood": {
    "mood": "震荡中性",
    "icon": "➖",
    "color": "#86868b",
    "confidence": 7,
    "dimensions": [
      {
        "label": "📈 趋势",
        "value": "震荡"
      },
      {
        "label": "💰 资金",
        "value": "中性"
      },
      {
        "label": "🌍 地缘",
        "value": "地缘缓和 · 利好"
      },
      {
        "label": "🏭 热点",
        "value": "AI科技 · 消费 · 金融"
      },
      {
        "label": "😊 情绪",
        "value": "中性"
      },
      {
        "label": "🏦 宏观",
        "value": "政策中性"
      }
    ],
    "summary": "整体震荡中性（7/10）。震荡，中性。地缘缓和 · 利好。中性。"
  },
  "experts": {
    "templeton": {
      "insight": "地缘缓和，情绪已price in。逆向机会在协议执行波折中被低估的航运和能源股。",
      "action": "逢低布局能源ETF，等待地缘溢价修复。"
    },
    "buffett": {
      "insight": "AI像互联网泡沫初期。Meta和谷歌的AI安全防护被破解，说明这个领域还是蛮荒时代，赢家未定。",
      "action": "关注已证明盈利的科技巨头和AI基础设施ETF。"
    },
    "munger": {
      "insight": "三层思维：①降息利好共识 ②力度可能超预期 ③利率高位时银行保险反受益。以色列央行的行动是信号。",
      "action": "不追利率敏感板块，关注保险和银行。"
    },
    "duan": {
      "insight": "科技龙头有网络效应，赢家通吃。苹果的AI布局+生态绑定是最确定的机会，腾讯也有机会。",
      "action": "逢低加仓苹果和腾讯，敢重仓敢持有。"
    }
  }
}