{
  "updateTime": "2026-05-26 21:50",
  "news": [
    {
      "rank": 3,
      "source": "新浪财经",
      "time": "2026-05-26 21:30",
      "title": "伊朗议员：霍尔木兹海峡潜在协议对伊朗'纯粹弊大于利'",
      "summary": "伊朗保守派议员、伊美谈判团队成员纳巴维安称，若协议以重新开放海峡换取解除制裁，对伊朗将是纯粹的损失。",
      "detail": "伊朗保守派议员、伊美谈判团队成员纳巴维安在社交平台X上发文称：若协议以重新开放海峡换取解除部分制裁，对伊朗国家利益将是'纯粹弊大于利'。与此同时，英国海上贸易行动中心通报，阿曼湾霍尔木兹海峡入海口附近一艘油轮发生外部爆炸，部分燃油泄漏入海，进一步加剧海峡地区紧张局势。"
    },
    {
      "rank": 1,
      "source": "新浪财经",
      "time": "2026-05-26 21:50",
      "title": "美股周二高开 美伊协议接近达成 纳指涨近1%",
      "summary": "美股高开，纳指涨0.94%，半导体板块领涨，美光科技涨超10%。美伊谈判取得进展，霍尔木兹海峡可能重新开放。",
      "detail": "北京时间5月26日晚，美股周二高开，道指涨0.21%报50686点，纳指涨0.92%报26590点，标普500涨0.51%报7511点。半导体板块强势，美光科技涨约10%，瑞银上调目标价至华尔街最高；AMD涨约4%。市场关注美伊协议进展，白宫经济顾问哈塞特表示若霍尔木兹海峡恢复通航，通胀将显著下降。"
    },
    {
      "rank": 2,
      "source": "华尔街见闻",
      "time": "2026-05-26 21:40",
      "title": "消息人士：解冻伊朗海外资金成伊美谈判主要分歧",
      "summary": "伊美谈判主要分歧在伊朗海外资金解冻问题。美方一度在承诺上后退，伊方坚持资金到账前协议不可能达成。",
      "detail": "据伊朗法尔斯通讯社26日报道，接近伊朗谈判团队的消息人士表示，伊美谈判主要分歧之一是伊朗海外资金解冻问题。美方一度在履行相关承诺上后退，但伊方坚持在约定资金到账之前，任何协议都不可能达成。卡塔尔方面协调后相关问题取得一定进展。伊朗已为所有可能情况作好准备。"
    },
    {
      "rank": 10,
      "source": "21世纪经济报道",
      "time": "2026-05-26 18:30",
      "title": "中国首富钟睒睒砸5亿跨界入局全固态电池",
      "summary": "农夫山泉创始人钟睒睒通过养生堂有限公司悄然入局全固态电池领域，投资规模约5亿元。",
      "detail": "2026年5月，农夫山泉创始人、中国首富钟睒睒通过其控制的养生堂有限公司悄然入局全固态电池领域，投资规模约5亿元。全固态电池被业界视为下一代电池的重要方向，宁德时代、比亚迪等头部企业均已布局。钟睒睒此次跨界或将加速全固态电池产业化进程，但技术路线和商业化时间表仍存不确定性。"
    },
    {
      "rank": 4,
      "source": "新浪财经",
      "time": "2026-05-26 21:20",
      "title": "小米Q1业绩会实录：手机尽量不涨价 汽车能完成全年交付目标",
      "summary": "小米Q1营收991.4亿元，调整后净利润60.7亿元。总裁卢伟冰表示手机尽量不涨价，汽车业务能完成全年交付目标。",
      "detail": "小米集团发布第一季度财报，营收991.4亿元，调整后净利润60.7亿元。财报电话会上，总裁卢伟冰表示手机业务在成本压力下尽量不涨价，通过供应链优化消化成本；汽车业务进展顺利，能完成全年交付目标。这是小米汽车发布后的首份完整季度财报，汽车业务毛利率环比改善。"
    },
    {
      "rank": 5,
      "source": "华尔街见闻",
      "time": "2026-05-26 21:00",
      "title": "欧盟将向波罗的海三国提供120亿欧元安全援助",
      "summary": "欧盟委员会主席冯德莱恩宣布，将通过'欧洲安全行动'计划向立陶宛、拉脱维亚和爱沙尼亚提供120亿欧元安全援助。",
      "detail": "当地时间5月26日，欧盟委员会主席冯德莱恩在访问立陶宛时宣布，将通过'欧洲安全行动'计划向波罗的海三国提供120亿欧元安全援助。此举旨在加强北约东翼防御能力，应对地缘安全挑战。援助将用于军事基础设施建设、联合演习和防空系统升级。"
    },
    {
      "rank": 9,
      "source": "华尔街见闻",
      "time": "2026-05-26 19:00",
      "title": "昇腾310等9款芯片通过安全可靠测评",
      "summary": "中国信息安全测评中心公布AI训练推理芯片测评结果，海思昇腾310、平头哥真武M530等9款芯片获I级安全可靠等级。",
      "detail": "据中国信息安全测评中心网站消息，5月26日，根据《安全可靠测评工作指南 V3.0》要求，中国信息安全测评中心与国家保密科技测评中心公布了AI训练推理芯片和数据库安全可靠测评结果。海思半导体送测的昇腾310、平头哥送测的真武M530等9款芯片获得'I级'安全可靠等级，标志国产AI芯片自主可控能力进一步提升。"
    },
    {
      "rank": 6,
      "source": "新浪财经",
      "time": "2026-05-26 20:30",
      "title": "3倍牛股二股东转让半数股份 34家机构7折接盘",
      "summary": "欧科亿第二大股东格林美拟询价转让股份，初步定价96.45元/股，较市价约7折，34家机构参与接盘。",
      "detail": "5月26日晚，欧科亿发布第二大股东格林美拟询价转让公司股份的初步定价公告。经向机构投资者询价后，初步确定转让价格为96.45元/股，较当日收盘价折价约30%。34家机构参与此次接盘。欧科亿此前为年内3倍牛股，此次大比例折价转让引发市场关注。"
    },
    {
      "rank": 7,
      "source": "中国证券报",
      "time": "2026-05-26 20:00",
      "title": "日收益翻几倍 理财'特种兵'盯上了'爆金币'",
      "summary": "R1低风险银行理财成为短线套利标的。招银理财某产品因短期收益波动大，吸引'理财特种兵'追逐日内收益。",
      "detail": "本是追求稳健的R1、R2级银行理财，如今却成了短线套利标的。有博主将4月29日成立的招银理财'招睿丰和30天持有期4号'作为套利案例，称其日内收益可翻数倍。业内人士提示，这种短期收益波动不代表产品真实回报率，投资者需警惕流动性风险和净值波动。"
    },
    {
      "rank": 8,
      "source": "新浪财经",
      "time": "2026-05-26 19:30",
      "title": "非法跨境投资整治触及香港保险'敏感神经'",
      "summary": "证监会等八部门联合印发跨境非法经营整治方案，继跨境券商后，香港保险跨境销售可能成为下一个监管重点。",
      "detail": "证监会等八部门联合印发《综合整治非法跨境证券期货基金经营活动实施方案》，将跨境券商推入风暴中心。市场关注跨境保险是否会成为下一个监管对象。近年来内地居民通过第三方中介购买香港保险规模增长迅速，监管机构对跨境展业合规性的关注度持续提升。"
    }
  ]
}